<?xml version='1.0' encoding="utf-8"?>
<toc version="2.0">
<!-- First tocitem specifies top level in Help browser Contents pane -->
<!-- This can be a roadmap page, as shown below, or a content page -->

    <tocitem target="msim_product_page.html">mSim Toolbox
        <!-- Nest tocitems to create hierarchical entries in  Contents-->
        <!-- To include icons, use the following syntax for tocitems: -->
        <!-- <tocitem target="foo.html" image="HelpIcon.NAME"> -->
        <!-- Title-of-Section </tocitem> -->
        <!-- where NAME is one of the following (use capital letters): -->
        <!-- FUNCTION, USER_GUIDE, EXAMPLES, BLOCK, GETTING_STARTED, -->
        <!-- DEMOS, RELEASE_NOTES --> 
        <!-- Icon images used for these entries are also stored in -->
        <!-- matlabroot/toolbox/matlab/icons -->
        <!-- A Getting Started Guide usually comes first -->
        <!-- Optional List of Examples, with hyperlinks to examples in other files -->
        <tocitem target="msim_requirements.html" image="HelpIcon.RELEASE_NOTES">
			 System Requirements
            </tocitem>
        
        <tocitem target="msim_help_main.html" image="HelpIcon.GETTING_STARTED">
            Getting Started
            <tocitem target="msim_help_main.html#1"> Introduction
            </tocitem>
            <tocitem target="msim_help_main.html#2"> Overview
            </tocitem>
            <tocitem target="msim_help_main.html#3"> Pre/Post processing
            </tocitem>
            <tocitem target="msim_help_main.html#4"> Limitations - To do list
            </tocitem>
		</tocitem>
		
		<tocitem target="msim_help_demos.html" image="HelpIcon.EXAMPLES">
            Examples
			<!-- 2nd and lower TOC levels usually have anchor IDs -->
			<tocitem target="mesh_gen_main.html">Mesh Generation
				<tocitem target="mesh_matlab_only.html">Using Matlab
				</tocitem>
				<tocitem target="mesh_matlab_shapef.html">Using Matlab and shapefiles
				</tocitem>
				<tocitem target="mesh_withquads.html">Generate quadrilateral mesh
				</tocitem>
				<tocitem target="mesh_arcgis.html">Using ArcGIS and Matlab
				</tocitem>
			</tocitem>
			
			<tocitem target="oneD_examp.html">1D Examples
				<tocitem target="oneD_examp.html#1">Flow simulation
				</tocitem>
				<tocitem target="msim_transp_1D.html">Transport simulation (To be completed)
				</tocitem>
			</tocitem>
			
			<tocitem target="twoD_examples_help.html">2D Examples
				<tocitem target="twoD_examples_help.html">Flow simulation
					<tocitem target="example_1_help.html">Triangular Elements
					</tocitem>
					<tocitem target="example_2_help.html">Quadrilateral Elements
					</tocitem>
				</tocitem>
			</tocitem>
			
			<tocitem target="hexa_flow.html">3D Examples
				<tocitem target="threeD_flow1_help.html">Flow simulation
				</tocitem>
			</tocitem>

			<tocitem target="NPSAT_examp.html">NPSAT Example
				<tocitem target="NPSAT_examp.html#1">Problem Definition
				</tocitem>
				<tocitem target="NPSAT_examp.html#2">Flow Simulation
				</tocitem>
				<tocitem target="NPSAT_examp.html#3">Particle Tracking
				</tocitem>
				<tocitem target="NPSAT_examp1.html">URF Computation
				</tocitem>
				<tocitem target="NPSAT_examp2.html">Prediction Phase
				</tocitem>
			</tocitem>
			
			<tocitem target="partTrack_demos.html">Particle Tracking
				<tocitem target="partTrack_comparison_deom.html">Comparison of Particle tracking modes
				</tocitem>
			</tocitem>
		</tocitem>
		
		<tocitem target="msim_function_categories.html" image="HelpIcon.FUNCTION"> Functions
			<tocitem target="msim_function_categories.html#1">mFlow
				<tocitem target="Assemble_LHS_help.html" image="HelpIcon.FUNCTION"> Assemble_LHS
				</tocitem>
				<tocitem target="Assemble_RHS_help.html" image="HelpIcon.FUNCTION"> Assemble_RHS
				</tocitem>
				<tocitem target="calcBKB_help.html" image="HelpIcon.FUNCTION"> calcBKB_help
					<tocitem target="calcBKBline_Lin_help.html" image="HelpIcon.FUNCTION"> calcBKBline_Lin
					</tocitem>
					<tocitem target="calcBKBline_quad_help.html" image="HelpIcon.FUNCTION"> calcBKBline_quad
					</tocitem>
					<tocitem target="calcBKBtriang_Lin_help.html" image="HelpIcon.FUNCTION"> calcBKBtriang_Lin
					</tocitem>
					<tocitem target="calcBKBtriang_quad_help.html" image="HelpIcon.FUNCTION"> calcBKBtriang_quad
					</tocitem>
					<tocitem target="calcBKBQuad_Lin_help.html" image="HelpIcon.FUNCTION"> calcBKBQuad_Lin
					</tocitem>
					<tocitem target="calcBKBQuad_quad_9_help.html" image="HelpIcon.FUNCTION"> calcBKBQuad_quad_9
					</tocitem>
					<tocitem target="calcBKBPrism_Lin_help.html" image="HelpIcon.FUNCTION"> calcBKBPrism_Lin
					</tocitem>
					<tocitem target="calcBKBPrism_quad_help.html" image="HelpIcon.FUNCTION"> calcBKBPrism_quad
					</tocitem>
					<tocitem target="calcBKBHex_Lin_help.html" image="HelpIcon.FUNCTION"> calcBKBHex_Lin
					</tocitem>
					<tocitem target="calcBKBHex_quad_27_help.html" image="HelpIcon.FUNCTION"> calcBKBHex_quad_27
					</tocitem>
				</tocitem>
				<tocitem target="initialize_BEM_help.html" image="HelpIcon.FUNCTION"> initialize_BEM
				</tocitem>
				<tocitem target="integr_order_help.html" image="HelpIcon.FUNCTION"> integr_order
				</tocitem>
				<tocitem target="interp_with_shapefnc_help.html" image="HelpIcon.FUNCTION"> interp_with_shapefnc
				</tocitem>
				<tocitem target="shapeDerivatives_help.html" image="HelpIcon.FUNCTION"> shapeDerivatives
					<tocitem target="shapeDerivLine_Lin_help.html" image="HelpIcon.FUNCTION"> shapeDerivLine_Lin
					</tocitem>
					<tocitem target="shapeDerivLine_quad_help.html" image="HelpIcon.FUNCTION"> shapeDerivLine_quad
					</tocitem>
					<tocitem target="shapeDerivTriang_Lin_help.html" image="HelpIcon.FUNCTION"> shapeDerivTriang_Lin
					</tocitem>
					<tocitem target="shapeDerivTriang_quad_help.html" image="HelpIcon.FUNCTION"> shapeDerivTriang_quad
					</tocitem>
					<tocitem target="shapeDerivQuad_Lin_help.html" image="HelpIcon.FUNCTION"> shapeDerivQuad_Lin
					</tocitem>
					<tocitem target="shapeDerivQuad_quad_9_help.html" image="HelpIcon.FUNCTION"> shapeDerivQuad_quad_9
					</tocitem>
					<tocitem target="shapeDerivPrism_Lin_help.html" image="HelpIcon.FUNCTION"> shapeDerivPrism_Lin
					</tocitem>
					<tocitem target="shapeDerivPrism_quad_help.html" image="HelpIcon.FUNCTION"> shapeDerivPrism_quad
					</tocitem>
					<tocitem target="shapeDerivHex_Lin_help.html" image="HelpIcon.FUNCTION"> shapeDerivHex_Lin
					</tocitem>
					<tocitem target="shapeDerivHex_quad_27_help.html" image="HelpIcon.FUNCTION"> shapeDerivHex_quad_27
					</tocitem>
				</tocitem>
				<tocitem target="shapefunctions_help.html" image="HelpIcon.FUNCTION"> shapefunctions
				</tocitem>
				<tocitem target="solve_system_help.html" image="HelpIcon.FUNCTION"> solve_system
				</tocitem>
			</tocitem>
			<tocitem target="msim_function_categories.html#2">mTrans
				<tocitem target="ADE1Danalytical_help.html" image="HelpIcon.FUNCTION"> ADE1Danalytical
				</tocitem>
				<tocitem target="Assemble_LHS_std_help.html" image="HelpIcon.FUNCTION"> Assemble_LHS_std
				</tocitem>
				<tocitem target="calcNvB_help.html" image="HelpIcon.FUNCTION"> calcNvB
					<tocitem target="calcNDBline_Lin_help.html" image="HelpIcon.FUNCTION"> calcNDBline_Lin
					</tocitem>
				</tocitem>
				<tocitem target="calcNLN_help.html" image="HelpIcon.FUNCTION"> calcNLN
				</tocitem>
				<tocitem target="DispCoeff_help.html" image="HelpIcon.FUNCTION"> DispCoeff
				</tocitem>
				<tocitem target="SteadyFlowTransport_help.html" image="HelpIcon.FUNCTION"> SteadyFlowTransport
				</tocitem>
			</tocitem>
			<tocitem target="msim_function_categories.html#3">mPart
				<tocitem target="ParticleTracking_main_help.html" image="HelpIcon.FUNCTION"> ParticleTracking_main
				</tocitem>
				<tocitem target="part_options_help.html" image="HelpIcon.FUNCTION"> part_options
				</tocitem>
			</tocitem>
			<tocitem target="msim_function_categories.html#4">mUtil
				<tocitem target="Build2Dmeshinfocpp_help.html" image="HelpIcon.FUNCTION"> Build2Dmeshinfocpp
				</tocitem>
				<tocitem target="Calc_Area_help.html" image="HelpIcon.FUNCTION"> Calc_Area
				</tocitem>
				<tocitem target="Calc_Barycenters_help.html" image="HelpIcon.FUNCTION"> Calc_Barycenters
				</tocitem>
				<tocitem target="Calc_volume_help.html" image="HelpIcon.FUNCTION"> Calc_volume
				</tocitem>
				<tocitem target="Centerfor2points_help.html" image="HelpIcon.FUNCTION"> Centerfor2points
				</tocitem>
				<tocitem target="CSGobj_v2_help.html" image="HelpIcon.FUNCTION"> CSGobj_v2
				</tocitem>
				<tocitem target="Dist_Point_LineSegment_help.html" image="HelpIcon.FUNCTION"> Dist_Point_LineSegment
				</tocitem>
				<tocitem target="extrude_mesh_help.html" image="HelpIcon.FUNCTION"> extrude_mesh
				</tocitem>
				<tocitem target="find_elem_id_point_help.html" image="HelpIcon.FUNCTION"> find_elem_id_point
				</tocitem>
				<tocitem target="helix_axis_help.html" image="HelpIcon.FUNCTION"> helix_axis
				</tocitem>
				<tocitem target="iscw_help.html" image="HelpIcon.FUNCTION"> iscw
				</tocitem>
				<tocitem target="mapElemto2D_help.html" image="HelpIcon.FUNCTION"> mapElemto2D
				</tocitem>
				<tocitem target="msim_mesh_options_help.html" image="HelpIcon.FUNCTION"> msim_mesh_options
				</tocitem>
				<tocitem target="read_2D_Gmsh_help.html" image="HelpIcon.FUNCTION"> read_2D_Gmsh
				</tocitem>
				<tocitem target="readArcGisASCIIfile_help.html" image="HelpIcon.FUNCTION"> readArcGisASCIIfile
				</tocitem>
				<tocitem target="WriteAscii4Raster_help.html" image="HelpIcon.FUNCTION"> WriteAscii4Raster
				</tocitem>
				<tocitem target="WriteVtkMesh_help.html" image="HelpIcon.FUNCTION"> WriteVtkMesh
				</tocitem>
			</tocitem>
			<tocitem target="msim_function_categories.html#5">mNPSAT
				<tocitem target="ComputeURF_help.html" image="HelpIcon.FUNCTION"> ComputeURF
				</tocitem>
				<tocitem target="ConvoluteURF_help.html" image="HelpIcon.FUNCTION"> ConvoluteURF
				</tocitem>
				<tocitem target="distribute_particle_streams_help.html" image="HelpIcon.FUNCTION"> distribute_particle_streams
				</tocitem>
				<tocitem target="distribute_particle_wells_help.html" image="HelpIcon.FUNCTION"> distribute_particle_wells
				</tocitem>
			</tocitem>
		</tocitem>
    </tocitem>
</toc>
